postgresfixture/__init__.py
postgresfixture/__main__.py
postgresfixture/cluster.py
postgresfixture/clusterfixture.py
postgresfixture/main.py
postgresfixture/utils.py
postgresfixture/testing/__init__.py
postgresfixture/tests/__init__.py
postgresfixture/tests/test_cluster.py
postgresfixture/tests/test_clusterfixture.py
postgresfixture/tests/test_main.py
postgresfixture-0.5.0.dist-info/METADATA
postgresfixture-0.5.0.dist-info/WHEEL
postgresfixture-0.5.0.dist-info/entry_points.txt
postgresfixture-0.5.0.dist-info/top_level.txt
postgresfixture-0.5.0.dist-info/RECORD
