Metadata-Version: 2.1
Name: postgresfixture
Version: 0.5.0
Summary: A fixture for creating PostgreSQL clusters and databases, and tearing them down again, intended for use during development and testing.
Classifier: Development Status :: 5 - Production/Stable
Classifier: Intended Audience :: Developers
Classifier: Intended Audience :: System Administrators
Classifier: Programming Language :: Python
Classifier: Programming Language :: Python :: 3
Classifier: Programming Language :: Python :: 3.5
Classifier: Programming Language :: Python :: 3.6
Classifier: Programming Language :: Python :: 3.7
Classifier: Programming Language :: Python :: 3.8
Classifier: Programming Language :: Python :: 3.9
Classifier: Programming Language :: Python :: 3.10
Classifier: Programming Language :: Python :: 3.11
Classifier: Programming Language :: Python :: 3.12
Classifier: Programming Language :: Python :: 3.13
Classifier: Topic :: Software Development :: Libraries
Requires-Dist: fixtures >=0.3.8
Requires-Dist: packaging
Requires-Dist: psycopg2 >=2.4.4
Requires-Dist: testtools >=0.9.14
Requires-Dist: testscenarios >=0.4
